[{"contact_country": "United States", "contact_email_address": "info@alaskaalpineadventures.com#mailto:info@alaskaalpineadventures.com#", "contact_state": "AK", "activity_code": "GH", "cua_business_name": "Alaska Alpine Adventures, LLC", "contact_city": "Anchorage", "Web_site": "www.alaskaalpineadventures.com", "contact_fax_num": "", "contact_address": "300 E. 76th Ave Unit B", "contact_postal_code": "99578", "contact_day_phone_num": "8775252577"}, {"contact_country": "United States", "contact_email_address": "info@alaskaalpineadventures.com#mailto:info@alaskaalpineadventures.com#", "contact_state": "AK", "activity_code": "BT", "cua_business_name": "Alaska Alpine Adventures, LLC", "contact_city": "Anchorage", "Web_site": "www.alaskaalpineadventures.com", "contact_fax_num": "", "contact_address": "300 E. 76th Ave Unit B", "contact_postal_code": "99578", "contact_day_phone_num": "8775252577"}, {"contact_country": "United States", "contact_email_address": "info@alaskaalpineadventures.com#mailto:info@alaskaalpineadventures.com#", "contact_state": "AK", "activity_code": "BP", "cua_business_name": "Alaska Alpine Adventures, LLC", "contact_city": "Anchorage", "Web_site": "www.alaskaalpineadventures.com", "contact_fax_num": "", "contact_address": "300 E. 76th Ave Unit B", "contact_postal_code": "99578", "contact_day_phone_num": "8775252577"}, {"contact_country": "United States", "contact_email_address": "danilob@mtsobek.com#mailto:danilob@mtsobek.com#", "contact_state": "CA", "activity_code": "BP", "cua_business_name": "Alaska Discovery, Inc.", "contact_city": "Emeryville", "Web_site": "www.mtsobek.com#http://www.mtsobek.com#", "contact_fax_num": "5105946001", "contact_address": "1266 66th Street, Suite 4", "contact_postal_code": "94608", "contact_day_phone_num": "5105946604"}, {"contact_country": "United States", "contact_email_address": "danilob@mtsobek.com#mailto:danilob@mtsobek.com#", "contact_state": "CA", "activity_code": "GH", "cua_business_name": "Alaska Discovery, Inc.", "contact_city": "Emeryville", "Web_site": "www.mtsobek.com#http://www.mtsobek.com#", "contact_fax_num": "5105946001", "contact_address": "1266 66th Street, Suite 4", "contact_postal_code": "94608", "contact_day_phone_num": "5105946604"}, {"contact_country": "United States", "contact_email_address": "caitlin@climbalaska.org#mailto:caitlin@climbalaska.org#", "contact_state": "AK", "activity_code": "BP", "cua_business_name": "Alaska Mountaineering School, LLC", "contact_city": "Talkeetna", "Web_site": "www.climbalaska.org", "contact_fax_num": "9077331362", "contact_address": "P.O. Box 566", "contact_postal_code": "99676", "contact_day_phone_num": "9077331016"}, {"contact_country": "United States", "contact_email_address": "caitlin@climbalaska.org#mailto:caitlin@climbalaska.org#", "contact_state": "AK", "activity_code": "MT", "cua_business_name": "Alaska Mountaineering School, LLC", "contact_city": "Talkeetna", "Web_site": "www.climbalaska.org", "contact_fax_num": "9077331362", "contact_address": "P.O. Box 566", "contact_postal_code": "99676", "contact_day_phone_num": "9077331016"}, {"contact_country": "United States", "contact_email_address": "caitlin@climbalaska.org#mailto:caitlin@climbalaska.org#", "contact_state": "AK", "activity_code": "MT", "cua_business_name": "Alaska Mountaineering School, LLC", "contact_city": "Talkeetna", "Web_site": "www.climbalaska.org", "contact_fax_num": "9077331362", "contact_address": "P.O. Box 566", "contact_postal_code": "99676", "contact_day_phone_num": "9077331016"}, {"contact_country": "United States", "contact_email_address": "caitlin@climbalaska.org#mailto:caitlin@climbalaska.org#", "contact_state": "AK", "activity_code": "BP", "cua_business_name": "Alaska Mountaineering School, LLC", "contact_city": "Talkeetna", "Web_site": "www.climbalaska.org", "contact_fax_num": "9077331362", "contact_address": "P.O. Box 566", "contact_postal_code": "99676", "contact_day_phone_num": "9077331016"}, {"contact_country": "United States", "contact_email_address": "arcticbackcountry@gmail.com#mailto:arcticbackcountry@gmail.com#", "contact_state": "AK", "activity_code": "AT", "cua_business_name": "Arctic Backcountry Flying Service, LLC", "contact_city": "Kotzebue", "Web_site": "www.arcticbackcountry.com#http://www.arcticbackcountry.com#", "contact_fax_num": "", "contact_address": "P.O. Box 672", "contact_postal_code": "99752", "contact_day_phone_num": "9074423200"}, {"contact_country": "United States", "contact_email_address": "garrett@arcticriverguides.com#mailto:garrett@arcticriverguides.com#", "contact_state": "AK", "activity_code": "GH", "cua_business_name": "Arctic River Guides", "contact_city": "Fairbanks", "Web_site": "", "contact_fax_num": "", "contact_address": "P.O. Box 84370", "contact_postal_code": "99708", "contact_day_phone_num": "9074880814"}, {"contact_country": "United States", "contact_email_address": "garrett@arcticriverguides.com#mailto:garrett@arcticriverguides.com#", "contact_state": "AK", "activity_code": "BT", "cua_business_name": "Arctic River Guides", "contact_city": "Fairbanks", "Web_site": "", "contact_fax_num": "", "contact_address": "P.O. Box 84370", "contact_postal_code": "99708", "contact_day_phone_num": "9074880814"}, {"contact_country": "United States", "contact_email_address": "garrett@arcticriverguides.com#mailto:garrett@arcticriverguides.com#", "contact_state": "AK", "activity_code": "BP", "cua_business_name": "Arctic River Guides", "contact_city": "Fairbanks", "Web_site": "", "contact_fax_num": "", "contact_address": "P.O. Box 84370", "contact_postal_code": "99708", "contact_day_phone_num": "9074880814"}, {"contact_country": "United States", "contact_email_address": "arctictreks@alaska.net#mailto:arctictreks@alaska.net#", "contact_state": "AK", "activity_code": "BP", "cua_business_name": "Arctic Treks", "contact_city": "Fairbanks", "Web_site": "www.arctictreksadventures.com", "contact_fax_num": "9074556522", "contact_address": "P.O. Box 73452", "contact_postal_code": "99707", "contact_day_phone_num": "9074556502"}, {"contact_country": "United States", "contact_email_address": "arctictreks@alaska.net#mailto:arctictreks@alaska.net#", "contact_state": "AK", "activity_code": "BT", "cua_business_name": "Arctic Treks", "contact_city": "Fairbanks", "Web_site": "www.arctictreksadventures.com", "contact_fax_num": "9074556522", "contact_address": "P.O. Box 73452", "contact_postal_code": "99707", "contact_day_phone_num": "9074556502"}, {"contact_country": "United States", "contact_email_address": "sally@arcticwild.com#mailto:sally@arcticwild.com#", "contact_state": "AK", "activity_code": "BP", "cua_business_name": "Arctic Wild, LLC", "contact_city": "Fairbanks", "Web_site": "www.arcticwild.com#http://www.arcticwild.com#", "contact_fax_num": "", "contact_address": "P.O. Box 80562", "contact_postal_code": "99708", "contact_day_phone_num": "9074798203"}, {"contact_country": "United States", "contact_email_address": "sally@arcticwild.com#mailto:sally@arcticwild.com#", "contact_state": "AK", "activity_code": "WA", "cua_business_name": "Arctic Wild, LLC", "contact_city": "Fairbanks", "Web_site": "www.arcticwild.com#http://www.arcticwild.com#", "contact_fax_num": "", "contact_address": "P.O. Box 80562", "contact_postal_code": "99708", "contact_day_phone_num": "9074798203"}, {"contact_country": "United States", "contact_email_address": "sally@arcticwild.com#mailto:sally@arcticwild.com#", "contact_state": "AK", "activity_code": "PH", "cua_business_name": "Arctic Wild, LLC", "contact_city": "Fairbanks", "Web_site": "www.arcticwild.com#http://www.arcticwild.com#", "contact_fax_num": "", "contact_address": "P.O. Box 80562", "contact_postal_code": "99708", "contact_day_phone_num": "9074798203"}, {"contact_country": "United States", "contact_email_address": "sally@arcticwild.com#mailto:sally@arcticwild.com#", "contact_state": "AK", "activity_code": "BT", "cua_business_name": "Arctic Wild, LLC", "contact_city": "Fairbanks", "Web_site": "www.arcticwild.com#http://www.arcticwild.com#", "contact_fax_num": "", "contact_address": "P.O. Box 80562", "contact_postal_code": "99708", "contact_day_phone_num": "9074798203"}, {"contact_country": "United States", "contact_email_address": "aoutfit@mtaonline.net#mailto:aoutfit@mtaonline.net#", "contact_state": "AK", "activity_code": "HT", "cua_business_name": "Arrowhead Outfitters, LLC", "contact_city": "Wasilla", "Web_site": "www.arrowheadoutfitters.com#http://www.arrowheadoutfitters.com#", "contact_fax_num": "9077467211", "contact_address": "5744 E. Rutan Avenue", "contact_postal_code": "99654", "contact_day_phone_num": "9077467744"}, {"contact_country": "United States", "contact_email_address": "aoutfit@mtaonline.net#mailto:aoutfit@mtaonline.net#", "contact_state": "AK", "activity_code": "SF", "cua_business_name": "Arrowhead Outfitters, LLC", "contact_city": "Wasilla", "Web_site": "www.arrowheadoutfitters.com#http://www.arrowheadoutfitters.com#", "contact_fax_num": "9077467211", "contact_address": "5744 E. Rutan Avenue", "contact_postal_code": "99654", "contact_day_phone_num": "9077467744"}, {"contact_country": "United States", "contact_email_address": "aoutfit@mtaonline.net#mailto:aoutfit@mtaonline.net#", "contact_state": "AK", "activity_code": "AT", "cua_business_name": "Arrowhead Outfitters, LLC", "contact_city": "Wasilla", "Web_site": "www.arrowheadoutfitters.com#http://www.arrowheadoutfitters.com#", "contact_fax_num": "9077467211", "contact_address": "5744 E. Rutan Avenue", "contact_postal_code": "99654", "contact_day_phone_num": "9077467744"}, {"contact_country": "United States", "contact_email_address": "flybettleslodge@gmail.com#mailto:flybettleslodge@gmail.com#", "contact_state": "AK", "activity_code": "IT", "cua_business_name": "Birchwood Aircraft Services, LLC", "contact_city": "Bettles", "Web_site": "", "contact_fax_num": "", "contact_address": "P.O. Box 27", "contact_postal_code": "99726", "contact_day_phone_num": "9076925111"}, {"contact_country": "United States", "contact_email_address": "flybettleslodge@gmail.com#mailto:flybettleslodge@gmail.com#", "contact_state": "AK", "activity_code": "AT", "cua_business_name": "Birchwood Aircraft Services, LLC", "contact_city": "Bettles", "Web_site": "", "contact_fax_num": "", "contact_address": "P.O. Box 27", "contact_postal_code": "99726", "contact_day_phone_num": "9076925111"}, {"contact_country": "United States", "contact_email_address": "flybettleslodge@gmail.com#mailto:flybettleslodge@gmail.com#", "contact_state": "AK", "activity_code": "SF", "cua_business_name": "Birchwood Aircraft Services, LLC", "contact_city": "Bettles", "Web_site": "", "contact_fax_num": "", "contact_address": "P.O. Box 27", "contact_postal_code": "99726", "contact_day_phone_num": "9076925111"}, {"contact_country": "United States", "contact_email_address": "airservice@brooksrange.com#mailto:airservice@brooksrange.com#", "contact_state": "AK", "activity_code": "AT", "cua_business_name": "Brooks Range Aviation", "contact_city": "Bettles", "Web_site": "www.brooksrange.com", "contact_fax_num": "9076922185", "contact_address": "P.O. Box 26010", "contact_postal_code": "99726", "contact_day_phone_num": "9076925444"}, {"contact_country": "United States", "contact_email_address": "airservice@brooksrange.com#mailto:airservice@brooksrange.com#", "contact_state": "AK", "activity_code": "HT", "cua_business_name": "Brooks Range Aviation", "contact_city": "Bettles", "Web_site": "www.brooksrange.com", "contact_fax_num": "9076922185", "contact_address": "P.O. Box 26010", "contact_postal_code": "99726", "contact_day_phone_num": "9076925444"}, {"contact_country": "", "contact_email_address": "flycoyoteair@gmail.com#mailto:flycoyoteair@gmail.com#", "contact_state": "AK", "activity_code": "AT", "cua_business_name": "Coyote Air, LLC", "contact_city": "Fairbanks", "Web_site": "www.flycoyote.com", "contact_fax_num": "9074795042", "contact_address": "2199 Nottingham Drive", "contact_postal_code": "99709", "contact_day_phone_num": "9074795995"}, {"contact_country": "United States", "contact_email_address": "info@expeditionsalaska.com#mailto:info@expeditionsalaska.com#", "contact_state": "AK", "activity_code": "BT", "cua_business_name": "Expeditions Alaska", "contact_city": "Copper Center", "Web_site": "www.expeditionsalaska.com#http://www.expeditionsalaska.com#", "contact_fax_num": "", "contact_address": "PO Box 412", "contact_postal_code": "99573", "contact_day_phone_num": "7709524549"}, {"contact_country": "United States", "contact_email_address": "info@expeditionsalaska.com#mailto:info@expeditionsalaska.com#", "contact_state": "AK", "activity_code": "BP", "cua_business_name": "Expeditions Alaska", "contact_city": "Copper Center", "Web_site": "www.expeditionsalaska.com#http://www.expeditionsalaska.com#", "contact_fax_num": "", "contact_address": "PO Box 412", "contact_postal_code": "99573", "contact_day_phone_num": "7709524549"}, {"contact_country": "United States", "contact_email_address": "goldeneagleoutfitters@gmail.com#mailto:goldeneagleoutfitters@gmail.com#", "contact_state": "AK", "activity_code": "AT", "cua_business_name": "Golden Eagle Outfitters, Inc.", "contact_city": "Delta Junction", "Web_site": "www.alaskawildernessexpeditions.com#http://www.alaskawildernessexpeditions.com#", "contact_fax_num": "9078954139", "contact_address": "P.O. Box 692", "contact_postal_code": "99737", "contact_day_phone_num": "9073882225"}, {"contact_country": "United States", "contact_email_address": "goldeneagleoutfitters@gmail.com#mailto:goldeneagleoutfitters@gmail.com#", "contact_state": "AK", "activity_code": "IT", "cua_business_name": "Golden Eagle Outfitters, Inc.", "contact_city": "Delta Junction", "Web_site": "www.alaskawildernessexpeditions.com#http://www.alaskawildernessexpeditions.com#", "contact_fax_num": "9078954139", "contact_address": "P.O. Box 692", "contact_postal_code": "99737", "contact_day_phone_num": "9073882225"}, {"contact_country": "United States", "contact_email_address": "iniakuk@gmail.com#mailto:iniakuk@gmail.com#", "contact_state": "AK", "activity_code": "WA", "cua_business_name": "Iniakuk Lake Wilderness Lodge, LLC", "contact_city": "Fairbanks", "Web_site": "www.gofarnorth.com", "contact_fax_num": "", "contact_address": "P.O. Box 80424", "contact_postal_code": "99708", "contact_day_phone_num": "9074796354"}, {"contact_country": "United States", "contact_email_address": "iniakuk@gmail.com#mailto:iniakuk@gmail.com#", "contact_state": "AK", "activity_code": "SF", "cua_business_name": "Iniakuk Lake Wilderness Lodge, LLC", "contact_city": "Fairbanks", "Web_site": "www.gofarnorth.com", "contact_fax_num": "", "contact_address": "P.O. Box 80424", "contact_postal_code": "99708", "contact_day_phone_num": "9074796354"}, {"contact_country": "United States", "contact_email_address": "iniakuk@gmail.com#mailto:iniakuk@gmail.com#", "contact_state": "AK", "activity_code": "GH", "cua_business_name": "Iniakuk Lake Wilderness Lodge, LLC", "contact_city": "Fairbanks", "Web_site": "www.gofarnorth.com", "contact_fax_num": "", "contact_address": "P.O. Box 80424", "contact_postal_code": "99708", "contact_day_phone_num": "9074796354"}, {"contact_country": "United States", "contact_email_address": "iniakuk@gmail.com#mailto:iniakuk@gmail.com#", "contact_state": "AK", "activity_code": "BP", "cua_business_name": "Iniakuk Lake Wilderness Lodge, LLC", "contact_city": "Fairbanks", "Web_site": "www.gofarnorth.com", "contact_fax_num": "", "contact_address": "P.O. Box 80424", "contact_postal_code": "99708", "contact_day_phone_num": "9074796354"}, {"contact_country": "United States", "contact_email_address": "iniakuk@gmail.com#mailto:iniakuk@gmail.com#", "contact_state": "AK", "activity_code": "BT", "cua_business_name": "Iniakuk Lake Wilderness Lodge, LLC", "contact_city": "Fairbanks", "Web_site": "www.gofarnorth.com", "contact_fax_num": "", "contact_address": "P.O. Box 80424", "contact_postal_code": "99708", "contact_day_phone_num": "9074796354"}, {"contact_country": "United States", "contact_email_address": "iniakuk@gmail.com#mailto:iniakuk@gmail.com#", "contact_state": "AK", "activity_code": "PH", "cua_business_name": "Iniakuk Lake Wilderness Lodge, LLC", "contact_city": "Fairbanks", "Web_site": "www.gofarnorth.com", "contact_fax_num": "", "contact_address": "P.O. Box 80424", "contact_postal_code": "99708", "contact_day_phone_num": "9074796354"}, {"contact_country": "United States", "contact_email_address": "jody@jodyyoung.com#mailto:jody@jodyyoung.com#", "contact_state": "UT", "activity_code": "GH", "cua_business_name": "Jody Young Adventure Travel", "contact_city": "Heber City", "Web_site": "www.jodyyoung.com#http://www.jodyyoung.com#", "contact_fax_num": "4356540444", "contact_address": "222 West 650 North", "contact_postal_code": "84032", "contact_day_phone_num": "4359011409"}, {"contact_country": "United States", "contact_email_address": "mghallen@yahoo.com#mailto:mghallen@yahoo.com#", "contact_state": "AK", "activity_code": "AT", "cua_business_name": "Mallen Air LLC", "contact_city": "Fairbanks", "Web_site": "", "contact_fax_num": "", "contact_address": "2805 Cowels Street, Apt #1", "contact_postal_code": "99701", "contact_day_phone_num": "9073857264"}, {"contact_country": "United States", "contact_email_address": "mountainmonarchsofalaska@gmail.com#mailto:mountainmonarchsofalaska@gmail.com#", "contact_state": "AK", "activity_code": "BT", "cua_business_name": "Mountain Monarchs of Alaska", "contact_city": "Soldotna", "Web_site": "www.mountainmonarchs.com#http://www.mountainmonarchs.com#", "contact_fax_num": "9076922185", "contact_address": "35555 Kenai Spur Highway #300", "contact_postal_code": "99669", "contact_day_phone_num": "9072524952"}, {"contact_country": "United States", "contact_email_address": "mountainmonarchsofalaska@gmail.com#mailto:mountainmonarchsofalaska@gmail.com#", "contact_state": "AK", "activity_code": "IT", "cua_business_name": "Mountain Monarchs of Alaska", "contact_city": "Soldotna", "Web_site": "www.mountainmonarchs.com#http://www.mountainmonarchs.com#", "contact_fax_num": "9076922185", "contact_address": "35555 Kenai Spur Highway #300", "contact_postal_code": "99669", "contact_day_phone_num": "9072524952"}, {"contact_country": "United States", "contact_email_address": "mountainmonarchsofalaska@gmail.com#mailto:mountainmonarchsofalaska@gmail.com#", "contact_state": "AK", "activity_code": "BP", "cua_business_name": "Mountain Monarchs of Alaska", "contact_city": "Soldotna", "Web_site": "www.mountainmonarchs.com#http://www.mountainmonarchs.com#", "contact_fax_num": "9076922185", "contact_address": "35555 Kenai Spur Highway #300", "contact_postal_code": "99669", "contact_day_phone_num": "9072524952"}, {"contact_country": "United States", "contact_email_address": "mountainmonarchsofalaska@gmail.com#mailto:mountainmonarchsofalaska@gmail.com#", "contact_state": "AK", "activity_code": "SF", "cua_business_name": "Mountain Monarchs of Alaska", "contact_city": "Soldotna", "Web_site": "www.mountainmonarchs.com#http://www.mountainmonarchs.com#", "contact_fax_num": "9076922185", "contact_address": "35555 Kenai Spur Highway #300", "contact_postal_code": "99669", "contact_day_phone_num": "9072524952"}, {"contact_country": "United States", "contact_email_address": "peaceofselby@gmail.com#mailto:peaceofselby@gmail.com#", "contact_state": "AK", "activity_code": "GH", "cua_business_name": "Peace Of Selby, Inc.", "contact_city": "Manley Hot Springs", "Web_site": "www.alaskawilderness.net", "contact_fax_num": "9076723206", "contact_address": "P.O. Box 86", "contact_postal_code": "99756", "contact_day_phone_num": "9076723206"}, {"contact_country": "United States", "contact_email_address": "peaceofselby@gmail.com#mailto:peaceofselby@gmail.com#", "contact_state": "AK", "activity_code": "BT", "cua_business_name": "Peace Of Selby, Inc.", "contact_city": "Manley Hot Springs", "Web_site": "www.alaskawilderness.net", "contact_fax_num": "9076723206", "contact_address": "P.O. Box 86", "contact_postal_code": "99756", "contact_day_phone_num": "9076723206"}, {"contact_country": "United States", "contact_email_address": "shadowaviationak@gmail.com#mailto:shadowaviationak@gmail.com#", "contact_state": "AK", "activity_code": "AT", "cua_business_name": "Shadow Aviation, Inc.", "contact_city": "Fairbanks", "Web_site": "", "contact_fax_num": "", "contact_address": "P.O. Box 83298", "contact_postal_code": "99708", "contact_day_phone_num": "9074517194"}, {"contact_country": "United States", "contact_email_address": "outings.permits@sierraclub.org#mailto:outings.permits@sierraclub.org#", "contact_state": "CA", "activity_code": "BP", "cua_business_name": "Sierra Club", "contact_city": "Oakland", "Web_site": "www.outings.sierraclub.org#http://www.outings.sierraclub.org#", "contact_fax_num": "4159775795", "contact_address": "2101 Webster Street, Suite 1300", "contact_postal_code": "94612", "contact_day_phone_num": "4159775690"}, {"contact_country": "United States", "contact_email_address": "swiftforkair@gmail.com#mailto:swiftforkair@gmail.com#", "contact_state": "AK", "activity_code": "AT", "cua_business_name": "Swift Fork Air, Inc", "contact_city": "Fairbanks", "Web_site": "", "contact_fax_num": "", "contact_address": "P.O. Box 84634", "contact_postal_code": "99708", "contact_day_phone_num": "9073780427"}, {"contact_country": "United States", "contact_email_address": "info@trekalaska.com#mailto:info@trekalaska.com#", "contact_state": "AK", "activity_code": "BP", "cua_business_name": "Trek Alaska, LLC", "contact_city": "Glennallen", "Web_site": "www.trekalaska.com", "contact_fax_num": "9073503710", "contact_address": "Box MXY, #46B", "contact_postal_code": "99588", "contact_day_phone_num": "9075541088"}, {"contact_country": "United States", "contact_email_address": "donnaclaus@mac.com#mailto:donnaclaus@mac.com#", "contact_state": "AK", "activity_code": "AT", "cua_business_name": "Ultima Thule Outfitters, Inc.", "contact_city": "Chitina", "Web_site": "www.ultimathulelodge.com", "contact_fax_num": "9076888805", "contact_address": "P.O. Box 109", "contact_postal_code": "99566", "contact_day_phone_num": "9076881200"}, {"contact_country": "United States", "contact_email_address": "rob@robkesselring.com#mailto:rob@robkesselring.com#", "contact_state": "MS", "activity_code": "SF", "cua_business_name": "Uncommon Seminars", "contact_city": "Lakeville", "Web_site": "", "contact_fax_num": "", "contact_address": "P.O. Box 1313", "contact_postal_code": "55044", "contact_day_phone_num": "9524328884"}, {"contact_country": "United States", "contact_email_address": "rob@robkesselring.com#mailto:rob@robkesselring.com#", "contact_state": "MS", "activity_code": "BP", "cua_business_name": "Uncommon Seminars", "contact_city": "Lakeville", "Web_site": "", "contact_fax_num": "", "contact_address": "P.O. Box 1313", "contact_postal_code": "55044", "contact_day_phone_num": "9524328884"}, {"contact_country": "United States", "contact_email_address": "rob@robkesselring.com#mailto:rob@robkesselring.com#", "contact_state": "MS", "activity_code": "BT", "cua_business_name": "Uncommon Seminars", "contact_city": "Lakeville", "Web_site": "", "contact_fax_num": "", "contact_address": "P.O. Box 1313", "contact_postal_code": "55044", "contact_day_phone_num": "9524328884"}, {"contact_country": "United States", "contact_email_address": "macgilladams@gmail.com#mailto:macgilladams@gmail.com#", "contact_state": "AK", "activity_code": "GH", "cua_business_name": "Wilderness Alaska", "contact_city": "Anchorage", "Web_site": "www.wildernessalaska.com", "contact_fax_num": "9073453967", "contact_address": "P.O. Box 113063", "contact_postal_code": "99511", "contact_day_phone_num": "9073453567"}, {"contact_country": "United States", "contact_email_address": "macgilladams@gmail.com#mailto:macgilladams@gmail.com#", "contact_state": "AK", "activity_code": "BT", "cua_business_name": "Wilderness Alaska", "contact_city": "Anchorage", "Web_site": "www.wildernessalaska.com", "contact_fax_num": "9073453967", "contact_address": "P.O. Box 113063", "contact_postal_code": "99511", "contact_day_phone_num": "9073453567"}, {"contact_country": "United States", "contact_email_address": "kaycie@wrightairservice.com#mailto:kaycie@wrightairservice.com#", "contact_state": "AK", "activity_code": "AT", "cua_business_name": "Wright Air Service, Inc.", "contact_city": "Fairbanks", "Web_site": "www.wrightair.net#http://www.wrightair.net#", "contact_fax_num": "9074740375", "contact_address": "P.O. Box 60142", "contact_postal_code": "99706", "contact_day_phone_num": "9074740502"}]